{
  "dependencies": {
    "mssql1": {
      "type": "mssql.local",
      "connectionId": "ddacassignmentContextConnection"
    },
    "secrets1": {
      "type": "secrets.user"
    },
    "mssql3": {
      "type": "mssql.local",
      "connectionId": "ddacassignmentNew2Context"
    },
    "storage1": {
      "resourceId": "/subscriptions/[parameters('subscriptionId')]/resourceGroups/[parameters('resourceGroupName')]/providers/Microsoft.Storage/storageAccounts/ddacassignmentstorages",
      "type": "storage.azure",
      "connectionId": "ddacassignmentstorage",
      "secretStore": "LocalSecretsFile"
    },
    "storage2": {
      "resourceId": "/subscriptions/[parameters('subscriptionId')]/resourcegroups/[parameters('resourceGroupName')]/providers/Microsoft.Storage/storageAccounts/ddacassignmentbstorage",
      "type": "storage.azure",
      "connectionId": "blobstorageconnection",
      "secretStore": null
    },
    "appInsights1": {
      "type": "appInsights.sdk"
    }
  }
}